pygeoboundaries_geolab/__init__.py
pygeoboundaries_geolab/countries_iso_dict.py
pygeoboundaries_geolab/get_gdf_test.py
pygeoboundaries_geolab/iso_codes.py
pygeoboundaries_geolab/pygeoboundaries.py
pygeoboundaries_geolab/pygeoboundaries_test.py
pygeoboundaries_geolab-0.0.4.dist-info/licenses/LICENSE
pygeoboundaries_geolab-0.0.4.dist-info/METADATA
pygeoboundaries_geolab-0.0.4.dist-info/WHEEL
pygeoboundaries_geolab-0.0.4.dist-info/top_level.txt
pygeoboundaries_geolab-0.0.4.dist-info/RECORD
