Metadata-Version: 2.4
Name: pygeoboundaries_geolab
Version: 0.0.4
License-File: LICENSE
Requires-Dist: geojson
Requires-Dist: requests_cache
Requires-Dist: geopandas
Requires-Dist: shapely
Requires-Dist: pytest
Requires-Dist: numpy
Dynamic: license-file
Dynamic: requires-dist
